mppsolar/__init__.py
mppsolar/daemon/__init__.py
mppsolar/daemon/daemon.py
mppsolar/daemon/daemon_disabled.py
mppsolar/daemon/daemon_openrc.py
mppsolar/daemon/daemon_systemd.py
mppsolar/daemon/pyinstaller_runtime.py
mppsolar/devices/__init__.py
mppsolar/devices/device.py
mppsolar/devices/jkbms.py
mppsolar/devices/mppsolar.py
mppsolar/helpers.py
mppsolar/inout/__init__.py
mppsolar/inout/baseio.py
mppsolar/inout/dalyserialio.py
mppsolar/inout/esp32io.py
mppsolar/inout/hidrawio.py
mppsolar/inout/jkbledelegate.py
mppsolar/inout/jkbleio.py
mppsolar/inout/jkserialio.py
mppsolar/inout/mqttio.py
mppsolar/inout/remotesocketio.py
mppsolar/inout/serialio.py
mppsolar/inout/testio.py
mppsolar/inout/vserialio.py
mppsolar/libs/__init__.py
mppsolar/libs/mqtt_manager.py
mppsolar/libs/mqttbroker_legacy.py
mppsolar/main.py
mppsolar/outputs/__init__.py
mppsolar/outputs/baseoutput.py
mppsolar/outputs/boxdraw.py
mppsolar/outputs/domoticz_autodiscover.py
mppsolar/outputs/domoticz_mqtt.py
mppsolar/outputs/hass_mqtt.py
mppsolar/outputs/hassd_mqtt.py
mppsolar/outputs/influx2_mqtt.py
mppsolar/outputs/influx_mqtt.py
mppsolar/outputs/json.py
mppsolar/outputs/json_mqtt.py
mppsolar/outputs/json_udp.py
mppsolar/outputs/json_units.py
mppsolar/outputs/mongo.py
mppsolar/outputs/mqtt.py
mppsolar/outputs/postgres.py
mppsolar/outputs/prom.py
mppsolar/outputs/prom_file.py
mppsolar/outputs/prom_push.py
mppsolar/outputs/prom_pushd.py
mppsolar/outputs/raw.py
mppsolar/outputs/screen.py
mppsolar/outputs/simple.py
mppsolar/outputs/simpleunits.py
mppsolar/outputs/tag_mqtt.py
mppsolar/outputs/value.py
mppsolar/protocols/__init__.py
mppsolar/protocols/abstractprotocol.py
mppsolar/protocols/daly.py
mppsolar/protocols/daly40.py
mppsolar/protocols/jk02.py
mppsolar/protocols/jk02_32.py
mppsolar/protocols/jk04.py
mppsolar/protocols/jk232.py
mppsolar/protocols/jk485.py
mppsolar/protocols/jkabstractprotocol.py
mppsolar/protocols/jkpb.py
mppsolar/protocols/jkserial.py
mppsolar/protocols/jkv11.py
mppsolar-0.16.56.dist-info/LICENSE
mppsolar-0.16.56.dist-info/METADATA
mppsolar-0.16.56.dist-info/WHEEL
mppsolar-0.16.56.dist-info/entry_points.txt
mppsolar-0.16.56.dist-info/RECORD
