Metadata-Version: 2.3
Name: mppsolar
Version: 0.16.56
Summary: Package to communicate with Solar inverters and BMSs
Author: John Blance
Requires-Python: >=3.11,<4.0
Classifier: Programming Language :: Python :: 3
Classifier: Programming Language :: Python :: 3.11
Classifier: Programming Language :: Python :: 3.12
Classifier: Programming Language :: Python :: 3.13
Provides-Extra: ble
Provides-Extra: dev
Provides-Extra: modbus
Provides-Extra: mongo
Provides-Extra: pgsql
Provides-Extra: systemd
Requires-Dist: bluepy (>=1.3.0,<2.0.0) ; extra == "ble" or extra == "dev"
Requires-Dist: cysystemd (>=1.6.2,<2.0.0) ; extra == "systemd"
Requires-Dist: paho-mqtt (>=1.6,<2.0.0)
Requires-Dist: psycopg2-binary (>=2.9.9) ; extra == "pgsql"
Requires-Dist: pymodbus (>=3.6.1) ; extra == "dev" or extra == "modbus"
Requires-Dist: pymongo (>=4.6.1) ; extra == "mongo"
Requires-Dist: pyserial (>3)
